notifications/__init__.py
notifications/base.py
notifications/discord.py
notifications/slack.py
notifeed-1.2.0.dist-info/LICENSE
notifeed-1.2.0.dist-info/METADATA
notifeed-1.2.0.dist-info/WHEEL
notifeed-1.2.0.dist-info/entry_points.txt
notifeed-1.2.0.dist-info/top_level.txt
notifeed-1.2.0.dist-info/RECORD
