Metadata-Version: 2.1
Name: notifeed
Version: 1.2.0
Summary: Automatically get notifications for new posts on your favorite RSS/Atom feeds.
Home-page: https://github.com/loganswartz/notifeed
Author: Logan Swartzendruber
Author-email: logan.swartzendruber@gmail.com
License: UNKNOWN
Platform: UNKNOWN
Classifier: Programming Language :: Python :: 3.8
Classifier: Operating System :: POSIX :: Linux
Classifier: Operating System :: MacOS
Classifier: Environment :: Console
Classifier: Topic :: Internet :: WWW/HTTP :: Dynamic Content :: News/Diary
Classifier: Topic :: Utilities
Requires-Python: >=3.8
License-File: LICENSE
Requires-Dist: aiohttp[speedups]
Requires-Dist: appdirs
Requires-Dist: atoma
Requires-Dist: bs4
Requires-Dist: click
Requires-Dist: requests
Requires-Dist: peewee
